pyramco/__init__.py
pyramco/pyramco.py
pyramco-0.9.722.dist-info/LICENSE
pyramco-0.9.722.dist-info/METADATA
pyramco-0.9.722.dist-info/WHEEL
pyramco-0.9.722.dist-info/top_level.txt
pyramco-0.9.722.dist-info/RECORD
