Metadata-Version: 2.1
Name: pyramco
Version: 0.9.722
Summary: A complete wrapper class for the RAMCO API
Home-page: https://github.com/mansard/pyramco
Author: Jeremey Bingham
Author-email: info@mansard.net
License: UNKNOWN
Platform: UNKNOWN
Classifier: Programming Language :: Python :: 3.7
Classifier: License :: OSI Approved :: MIT License
Classifier: Operating System :: OS Independent
Classifier: Development Status :: 4 - Beta
Requires-Python: >=3.7
Requires-Dist: requests
